poker/__init__.py
poker/_common.py
poker/card.py
poker/commands.py
poker/constants.py
poker/hand.py
poker/handhistory.py
poker/strategy.py
poker/room/__init__.py
poker/room/fulltiltpoker.py
poker/room/pkr.py
poker/room/pokerstars.py
poker/website/__init__.py
poker/website/pocketfives.py
poker/website/pokerstars.py
poker/website/twoplustwo.py
poker-0.23.1.dist-info/METADATA
poker-0.23.1.dist-info/RECORD
poker-0.23.1.dist-info/WHEEL
poker-0.23.1.dist-info/entry_points.txt
poker-0.23.1.dist-info/pbr.json
poker-0.23.1.dist-info/top_level.txt
