Metadata-Version: 2.1
Name: poker
Version: 0.23.1
Summary: Poker Framework
Home-page: https://github.com/pokerregion/poker
Author: Kiss György
Author-email: kissgyorgy@me.com
License: MIT
Keywords: poker
Platform: UNKNOWN
Classifier: Intended Audience :: Developers
Classifier: Programming Language :: Python
Classifier: Programming Language :: Python :: 2
Classifier: Programming Language :: Python :: 2.7
Requires-Dist: pytz
Requires-Dist: requests
Requires-Dist: lxml
Requires-Dist: python-dateutil
Requires-Dist: parsedatetime
Requires-Dist: cached-property
Requires-Dist: click
Requires-Dist: enum34
Requires-Dist: pathlib
Requires-Dist: configparser
Requires-Dist: zope.interface
Requires-Dist: attrs
